tripleo_repos/__init__.py
tripleo_repos/main.py
tripleo_repos/tests/__init__.py
tripleo_repos/tests/test_main.py
tripleo_repos-0.1.0.dist-info/AUTHORS
tripleo_repos-0.1.0.dist-info/LICENSE
tripleo_repos-0.1.0.dist-info/METADATA
tripleo_repos-0.1.0.dist-info/WHEEL
tripleo_repos-0.1.0.dist-info/entry_points.txt
tripleo_repos-0.1.0.dist-info/pbr.json
tripleo_repos-0.1.0.dist-info/top_level.txt
tripleo_repos-0.1.0.dist-info/RECORD
